seamm_cookiecutter/__init__.py
seamm_cookiecutter/_version.py
seamm_cookiecutter/seamm_cookiecutter.py
seamm_cookiecutter/plug-in/cookiecutter.json
seamm_cookiecutter/plug-in/hooks/post_gen_project.py
seamm_cookiecutter/plug-in/hooks/pre_gen_project.py
seamm_cookiecutter/plug-in/{{cookiecutter.repo_name}}/.codecov.yml
seamm_cookiecutter/plug-in/{{cookiecutter.repo_name}}/.editorconfig
seamm_cookiecutter/plug-in/{{cookiecutter.repo_name}}/.gitignore
seamm_cookiecutter/plug-in/{{cookiecutter.repo_name}}/.lgtm.yml
seamm_cookiecutter/plug-in/{{cookiecutter.repo_name}}/AUTHORS.rst
seamm_cookiecutter/plug-in/{{cookiecutter.repo_name}}/CONTRIBUTING.rst
seamm_cookiecutter/plug-in/{{cookiecutter.repo_name}}/HISTORY.rst
seamm_cookiecutter/plug-in/{{cookiecutter.repo_name}}/LICENSE
seamm_cookiecutter/plug-in/{{cookiecutter.repo_name}}/MANIFEST.in
seamm_cookiecutter/plug-in/{{cookiecutter.repo_name}}/Makefile
seamm_cookiecutter/plug-in/{{cookiecutter.repo_name}}/README.rst
seamm_cookiecutter/plug-in/{{cookiecutter.repo_name}}/requirements.txt
seamm_cookiecutter/plug-in/{{cookiecutter.repo_name}}/requirements_dev.txt
seamm_cookiecutter/plug-in/{{cookiecutter.repo_name}}/requirements_install.txt
seamm_cookiecutter/plug-in/{{cookiecutter.repo_name}}/setup.cfg
seamm_cookiecutter/plug-in/{{cookiecutter.repo_name}}/setup.py
seamm_cookiecutter/plug-in/{{cookiecutter.repo_name}}/versioneer.py
seamm_cookiecutter/plug-in/{{cookiecutter.repo_name}}/.github/ISSUE_TEMPLATE.md
seamm_cookiecutter/plug-in/{{cookiecutter.repo_name}}/.github/workflows/BranchCI.yaml
seamm_cookiecutter/plug-in/{{cookiecutter.repo_name}}/.github/workflows/CI.yaml
seamm_cookiecutter/plug-in/{{cookiecutter.repo_name}}/.github/workflows/Docs.yaml
seamm_cookiecutter/plug-in/{{cookiecutter.repo_name}}/.github/workflows/Release.yaml
seamm_cookiecutter/plug-in/{{cookiecutter.repo_name}}/devtools/README.md
seamm_cookiecutter/plug-in/{{cookiecutter.repo_name}}/devtools/conda-envs/test_env.yaml
seamm_cookiecutter-2022.10.20.dist-info/LICENSE
seamm_cookiecutter-2022.10.20.dist-info/METADATA
seamm_cookiecutter-2022.10.20.dist-info/WHEEL
seamm_cookiecutter-2022.10.20.dist-info/entry_points.txt
seamm_cookiecutter-2022.10.20.dist-info/top_level.txt
seamm_cookiecutter-2022.10.20.dist-info/RECORD
